retro_data_structures/__init__.py
retro_data_structures/__main__.py
retro_data_structures/asset_manager.py
retro_data_structures/base_resource.py
retro_data_structures/cli.py
retro_data_structures/common_types.py
retro_data_structures/compression.py
retro_data_structures/crc.py
retro_data_structures/data_section.py
retro_data_structures/dependencies.py
retro_data_structures/exceptions.py
retro_data_structures/game_check.py
retro_data_structures/property_template.py
retro_data_structures/version.py
retro_data_structures/adapters/__init__.py
retro_data_structures/adapters/enum_adapter.py
retro_data_structures/adapters/offset.py
retro_data_structures/construct_extensions/__init__.py
retro_data_structures/construct_extensions/alignment.py
retro_data_structures/construct_extensions/dict.py
retro_data_structures/construct_extensions/json.py
retro_data_structures/construct_extensions/misc.py
retro_data_structures/construct_extensions/version.py
retro_data_structures/conversion/__init__.py
retro_data_structures/conversion/ancs.py
retro_data_structures/conversion/anim.py
retro_data_structures/conversion/asset_converter.py
retro_data_structures/conversion/cinf.py
retro_data_structures/conversion/cmdl.py
retro_data_structures/conversion/conversions.py
retro_data_structures/conversion/cskr.py
retro_data_structures/conversion/errors.py
retro_data_structures/conversion/evnt.py
retro_data_structures/conversion/part.py
retro_data_structures/conversion/txtr.py
retro_data_structures/enums/.gitignore
retro_data_structures/enums/__init__.py
retro_data_structures/enums/corruption.py
retro_data_structures/enums/dkc_returns.py
retro_data_structures/enums/echoes.py
retro_data_structures/enums/prime.py
retro_data_structures/formats/__init__.py
retro_data_structures/formats/ancs.py
retro_data_structures/formats/anim.py
retro_data_structures/formats/area_collision.py
retro_data_structures/formats/arot.py
retro_data_structures/formats/char.py
retro_data_structures/formats/cinf.py
retro_data_structures-0.10.1.dist-info/LICENSE
retro_data_structures-0.10.1.dist-info/METADATA
retro_data_structures-0.10.1.dist-info/WHEEL
retro_data_structures-0.10.1.dist-info/top_level.txt
retro_data_structures-0.10.1.dist-info/RECORD
