Metadata-Version: 2.1
Name: retro-data-structures
Version: 0.10.1
Summary: Construct file definitions for the Retro Studios game engine files
Classifier: License :: OSI Approved :: MIT License
Classifier: Development Status :: 3 - Alpha
Classifier: Intended Audience :: Developers
Classifier: Programming Language :: Python :: 3.8
Classifier: Programming Language :: Python :: 3.9
Classifier: Programming Language :: Python :: 3.10
Requires-Python: >=3.8
License-File: LICENSE
Requires-Dist: construct (>=2.10.0)
Requires-Dist: lzokay
Requires-Dist: nod (>=1.7.0)
